sage/__init__.py
sage/core.py
sage/datasets.py
sage/grouped_imputers.py
sage/imputers.py
sage/iterated_estimator.py
sage/kernel_estimator.py
sage/permutation_estimator.py
sage/plotting.py
sage/sign_estimator.py
sage/utils.py
sage_importance-0.0.6.dist-info/LICENSE
sage_importance-0.0.6.dist-info/METADATA
sage_importance-0.0.6.dist-info/WHEEL
sage_importance-0.0.6.dist-info/top_level.txt
sage_importance-0.0.6.dist-info/RECORD
