Metadata-Version: 2.1
Name: sage-importance
Version: 0.0.6
Summary: For calculating global feature importance using Shapley values.
Author-email: Ian Covert <ian.covert@gmail.com>
License: MIT License
Project-URL: Repository, https://github.com/iancovert/sage/
Classifier: Intended Audience :: Science/Research
Classifier: License :: OSI Approved :: MIT License
Classifier: Operating System :: OS Independent
Classifier: Programming Language :: Python :: 3
Classifier: Topic :: Scientific/Engineering
Requires-Python: >=3.8
License-File: LICENSE
Requires-Dist: joblib
Requires-Dist: matplotlib
Requires-Dist: numpy
Requires-Dist: scipy
Requires-Dist: tqdm
Provides-Extra: dev
Requires-Dist: build ; extra == 'dev'
Requires-Dist: pre-commit ; extra == 'dev'
Provides-Extra: notebook
Requires-Dist: catboost ; extra == 'notebook'
Requires-Dist: ipykernel ; extra == 'notebook'
Requires-Dist: gender-guesser ; extra == 'notebook'
Requires-Dist: pandas ; extra == 'notebook'
Requires-Dist: tensorflow ; extra == 'notebook'
Requires-Dist: torch ; extra == 'notebook'
Requires-Dist: torchvision ; extra == 'notebook'
Requires-Dist: scikit-learn ; extra == 'notebook'
Requires-Dist: xgboost ; extra == 'notebook'
